<annotation>
	<filename>1311132744.jpg</filename>
	<size>
		<width>500</width>
		<height>328</height>
		<depth>3</depth>
	</size>
	<object>
		<name>8261</name>
		<bndbox>
			<xmin>1</xmin>
			<ymin>33</ymin>
			<xmax>392</xmax>
			<ymax>313</ymax>
		</bndbox>
	</object>
	<object>
		<name>8262</name>
		<bndbox>
			<xmin>1</xmin>
			<ymin>2</ymin>
			<xmax>498</xmax>
			<ymax>327</ymax>
		</bndbox>
	</object>
	<object>
		<name>8263</name>
		<bndbox>
			<xmin>171</xmin>
			<ymin>104</ymin>
			<xmax>256</xmax>
			<ymax>171</ymax>
		</bndbox>
	</object>
	<object>
		<name>8264</name>
		<bndbox>
			<xmin>297</xmin>
			<ymin>124</ymin>
			<xmax>341</xmax>
			<ymax>170</ymax>
		</bndbox>
	</object>
	<object>
		<name>8265</name>
		<bndbox>
			<xmin>286</xmin>
			<ymin>76</ymin>
			<xmax>397</xmax>
			<ymax>176</ymax>
		</bndbox>
	</object>
</annotation>