<annotation>
	<filename>1391386453.jpg</filename>
	<size>
		<width>334</width>
		<height>500</height>
		<depth>3</depth>
	</size>
	<object>
		<name>10950</name>
		<bndbox>
			<xmin>101</xmin>
			<ymin>72</ymin>
			<xmax>256</xmax>
			<ymax>445</ymax>
		</bndbox>
	</object>
	<object>
		<name>10951</name>
		<bndbox>
			<xmin>103</xmin>
			<ymin>122</ymin>
			<xmax>257</xmax>
			<ymax>442</ymax>
		</bndbox>
	</object>
	<object>
		<name>10956</name>
		<bndbox>
			<xmin>1</xmin>
			<ymin>1</ymin>
			<xmax>334</xmax>
			<ymax>500</ymax>
		</bndbox>
	</object>
	<object>
		<name>10953</name>
		<bndbox>
			<xmin>281</xmin>
			<ymin>51</ymin>
			<xmax>320</xmax>
			<ymax>119</ymax>
		</bndbox>
	</object>
	<object>
		<name>10952</name>
		<bndbox>
			<xmin>261</xmin>
			<ymin>1</ymin>
			<xmax>334</xmax>
			<ymax>225</ymax>
		</bndbox>
	</object>
	<object>
		<name>10954</name>
		<bndbox>
			<xmin>107</xmin>
			<ymin>1</ymin>
			<xmax>331</xmax>
			<ymax>287</ymax>
		</bndbox>
	</object>
	<object>
		<name>10954</name>
		<bndbox>
			<xmin>264</xmin>
			<ymin>114</ymin>
			<xmax>334</xmax>
			<ymax>125</ymax>
		</bndbox>
	</object>
	<object>
		<name>10958</name>
		<bndbox>
			<xmin>1</xmin>
			<ymin>99</ymin>
			<xmax>80</xmax>
			<ymax>470</ymax>
		</bndbox>
	</object>
	<object>
		<name>10958</name>
		<bndbox>
			<xmin>238</xmin>
			<ymin>126</ymin>
			<xmax>317</xmax>
			<ymax>383</ymax>
		</bndbox>
	</object>
	<object>
		<name>10958</name>
		<bndbox>
			<xmin>108</xmin>
			<ymin>174</ymin>
			<xmax>166</xmax>
			<ymax>329</ymax>
		</bndbox>
	</object>
	<object>
		<name>10957</name>
		<bndbox>
			<xmin>1</xmin>
			<ymin>288</ymin>
			<xmax>334</xmax>
			<ymax>500</ymax>
		</bndbox>
	</object>
	<object>
		<name>10955</name>
		<bndbox>
			<xmin>221</xmin>
			<ymin>137</ymin>
			<xmax>258</xmax>
			<ymax>241</ymax>
		</bndbox>
	</object>
	<object>
		<name>10955</name>
		<bndbox>
			<xmin>154</xmin>
			<ymin>135</ymin>
			<xmax>170</xmax>
			<ymax>220</ymax>
		</bndbox>
	</object>
	<object>
		<name>10961</name>
		<scene>0</scene>
		<nobndbox>1</nobndbox>
	</object>
	<object>
		<name>10960</name>
		<scene>1</scene>
		<nobndbox>0</nobndbox>
	</object>
	<object>
		<name>10959</name>
		<scene>1</scene>
		<nobndbox>1</nobndbox>
	</object>
</annotation>