<annotation>
	<filename>1679732375.jpg</filename>
	<size>
		<width>500</width>
		<height>334</height>
		<depth>3</depth>
	</size>
	<object>
		<name>18638</name>
		<name>18646</name>
		<bndbox>
			<xmin>204</xmin>
			<ymin>211</ymin>
			<xmax>285</xmax>
			<ymax>328</ymax>
		</bndbox>
	</object>
	<object>
		<name>18638</name>
		<bndbox>
			<xmin>204</xmin>
			<ymin>208</ymin>
			<xmax>318</xmax>
			<ymax>332</ymax>
		</bndbox>
	</object>
	<object>
		<name>18639</name>
		<bndbox>
			<xmin>127</xmin>
			<ymin>255</ymin>
			<xmax>327</xmax>
			<ymax>312</ymax>
		</bndbox>
	</object>
	<object>
		<name>18642</name>
		<bndbox>
			<xmin>1</xmin>
			<ymin>194</ymin>
			<xmax>499</xmax>
			<ymax>333</ymax>
		</bndbox>
	</object>
	<object>
		<name>18645</name>
		<bndbox>
			<xmin>1</xmin>
			<ymin>286</ymin>
			<xmax>484</xmax>
			<ymax>304</ymax>
		</bndbox>
	</object>
	<object>
		<name>18646</name>
		<name>18648</name>
		<bndbox>
			<xmin>265</xmin>
			<ymin>209</ymin>
			<xmax>319</xmax>
			<ymax>327</ymax>
		</bndbox>
	</object>
	<object>
		<name>18647</name>
		<bndbox>
			<xmin>227</xmin>
			<ymin>207</ymin>
			<xmax>302</xmax>
			<ymax>233</ymax>
		</bndbox>
	</object>
	<object>
		<name>18649</name>
		<bndbox>
			<xmin>2</xmin>
			<ymin>1</ymin>
			<xmax>71</xmax>
			<ymax>334</ymax>
		</bndbox>
	</object>
	<object>
		<name>18649</name>
		<name>18650</name>
		<bndbox>
			<xmin>415</xmin>
			<ymin>1</ymin>
			<xmax>452</xmax>
			<ymax>299</ymax>
		</bndbox>
	</object>
	<object>
		<name>18650</name>
		<bndbox>
			<xmin>11</xmin>
			<ymin>11</ymin>
			<xmax>78</xmax>
			<ymax>334</ymax>
		</bndbox>
	</object>
	<object>
		<name>18651</name>
		<bndbox>
			<xmin>208</xmin>
			<ymin>233</ymin>
			<xmax>277</xmax>
			<ymax>267</ymax>
		</bndbox>
	</object>
	<object>
		<name>18640</name>
		<scene>0</scene>
		<nobndbox>1</nobndbox>
	</object>
	<object>
		<name>18641</name>
		<scene>0</scene>
		<nobndbox>1</nobndbox>
	</object>
	<object>
		<name>18644</name>
		<scene>0</scene>
		<nobndbox>1</nobndbox>
	</object>
</annotation>