<annotation>
	<filename>2196284168.jpg</filename>
	<size>
		<width>303</width>
		<height>500</height>
		<depth>3</depth>
	</size>
	<object>
		<name>33513</name>
		<bndbox>
			<xmin>31</xmin>
			<ymin>93</ymin>
			<xmax>298</xmax>
			<ymax>478</ymax>
		</bndbox>
	</object>
	<object>
		<name>33514</name>
		<name>33516</name>
		<bndbox>
			<xmin>1</xmin>
			<ymin>169</ymin>
			<xmax>303</xmax>
			<ymax>500</ymax>
		</bndbox>
	</object>
	<object>
		<name>33516</name>
		<bndbox>
			<xmin>19</xmin>
			<ymin>130</ymin>
			<xmax>302</xmax>
			<ymax>289</ymax>
		</bndbox>
	</object>
	<object>
		<name>33517</name>
		<bndbox>
			<xmin>156</xmin>
			<ymin>236</ymin>
			<xmax>239</xmax>
			<ymax>354</ymax>
		</bndbox>
	</object>
</annotation>