<annotation>
	<filename>2274602044.jpg</filename>
	<size>
		<width>500</width>
		<height>301</height>
		<depth>3</depth>
	</size>
	<object>
		<name>38352</name>
		<bndbox>
			<xmin>181</xmin>
			<ymin>71</ymin>
			<xmax>332</xmax>
			<ymax>279</ymax>
		</bndbox>
	</object>
	<object>
		<name>38353</name>
		<bndbox>
			<xmin>116</xmin>
			<ymin>125</ymin>
			<xmax>336</xmax>
			<ymax>288</ymax>
		</bndbox>
	</object>
	<object>
		<name>38354</name>
		<bndbox>
			<xmin>282</xmin>
			<ymin>138</ymin>
			<xmax>331</xmax>
			<ymax>269</ymax>
		</bndbox>
	</object>
	<object>
		<name>38355</name>
		<bndbox>
			<xmin>181</xmin>
			<ymin>90</ymin>
			<xmax>286</xmax>
			<ymax>205</ymax>
		</bndbox>
	</object>
	<object>
		<name>38355</name>
		<bndbox>
			<xmin>180</xmin>
			<ymin>99</ymin>
			<xmax>272</xmax>
			<ymax>192</ymax>
		</bndbox>
	</object>
	<object>
		<name>38356</name>
		<bndbox>
			<xmin>291</xmin>
			<ymin>175</ymin>
			<xmax>324</xmax>
			<ymax>193</ymax>
		</bndbox>
	</object>
	<object>
		<name>38356</name>
		<bndbox>
			<xmin>291</xmin>
			<ymin>171</ymin>
			<xmax>322</xmax>
			<ymax>190</ymax>
		</bndbox>
	</object>
	<object>
		<name>38357</name>
		<scene>0</scene>
		<nobndbox>1</nobndbox>
	</object>
</annotation>