<annotation>
	<filename>2501548593.jpg</filename>
	<size>
		<width>334</width>
		<height>500</height>
		<depth>3</depth>
	</size>
	<object>
		<name>53579</name>
		<name>53583</name>
		<name>53587</name>
		<bndbox>
			<xmin>26</xmin>
			<ymin>50</ymin>
			<xmax>122</xmax>
			<ymax>386</ymax>
		</bndbox>
	</object>
	<object>
		<name>53579</name>
		<bndbox>
			<xmin>26</xmin>
			<ymin>42</ymin>
			<xmax>184</xmax>
			<ymax>445</ymax>
		</bndbox>
	</object>
	<object>
		<name>53581</name>
		<bndbox>
			<xmin>46</xmin>
			<ymin>37</ymin>
			<xmax>87</xmax>
			<ymax>75</ymax>
		</bndbox>
	</object>
	<object>
		<name>53582</name>
		<name>53587</name>
		<bndbox>
			<xmin>60</xmin>
			<ymin>41</ymin>
			<xmax>184</xmax>
			<ymax>443</ymax>
		</bndbox>
	</object>
	<object>
		<name>53585</name>
		<bndbox>
			<xmin>29</xmin>
			<ymin>106</ymin>
			<xmax>333</xmax>
			<ymax>280</ymax>
		</bndbox>
	</object>
	<object>
		<name>53580</name>
		<scene>0</scene>
		<nobndbox>1</nobndbox>
	</object>
	<object>
		<name>53584</name>
		<scene>0</scene>
		<nobndbox>1</nobndbox>
	</object>
</annotation>