<annotation>
	<filename>2511787709.jpg</filename>
	<size>
		<width>500</width>
		<height>332</height>
		<depth>3</depth>
	</size>
	<object>
		<name>54339</name>
		<bndbox>
			<xmin>100</xmin>
			<ymin>59</ymin>
			<xmax>332</xmax>
			<ymax>332</ymax>
		</bndbox>
	</object>
	<object>
		<name>54340</name>
		<bndbox>
			<xmin>79</xmin>
			<ymin>135</ymin>
			<xmax>261</xmax>
			<ymax>332</ymax>
		</bndbox>
	</object>
	<object>
		<name>54341</name>
		<bndbox>
			<xmin>2</xmin>
			<ymin>2</ymin>
			<xmax>401</xmax>
			<ymax>332</ymax>
		</bndbox>
	</object>
	<object>
		<name>54342</name>
		<bndbox>
			<xmin>214</xmin>
			<ymin>139</ymin>
			<xmax>320</xmax>
			<ymax>299</ymax>
		</bndbox>
	</object>
	<object>
		<name>54343</name>
		<bndbox>
			<xmin>103</xmin>
			<ymin>158</ymin>
			<xmax>151</xmax>
			<ymax>171</ymax>
		</bndbox>
	</object>
	<object>
		<name>54345</name>
		<bndbox>
			<xmin>213</xmin>
			<ymin>60</ymin>
			<xmax>328</xmax>
			<ymax>187</ymax>
		</bndbox>
	</object>
	<object>
		<name>54345</name>
		<bndbox>
			<xmin>172</xmin>
			<ymin>180</ymin>
			<xmax>261</xmax>
			<ymax>319</ymax>
		</bndbox>
	</object>
	<object>
		<name>54346</name>
		<bndbox>
			<xmin>221</xmin>
			<ymin>94</ymin>
			<xmax>284</xmax>
			<ymax>127</ymax>
		</bndbox>
	</object>
	<object>
		<name>54348</name>
		<bndbox>
			<xmin>101</xmin>
			<ymin>153</ymin>
			<xmax>111</xmax>
			<ymax>165</ymax>
		</bndbox>
	</object>
</annotation>