<annotation>
	<filename>2632463480.jpg</filename>
	<size>
		<width>337</width>
		<height>500</height>
		<depth>3</depth>
	</size>
	<object>
		<name>62746</name>
		<name>62747</name>
		<bndbox>
			<xmin>178</xmin>
			<ymin>337</ymin>
			<xmax>225</xmax>
			<ymax>449</ymax>
		</bndbox>
	</object>
	<object>
		<name>62746</name>
		<bndbox>
			<xmin>226</xmin>
			<ymin>347</ymin>
			<xmax>266</xmax>
			<ymax>453</ymax>
		</bndbox>
	</object>
	<object>
		<name>62748</name>
		<bndbox>
			<xmin>65</xmin>
			<ymin>67</ymin>
			<xmax>277</xmax>
			<ymax>454</ymax>
		</bndbox>
	</object>
	<object>
		<name>62749</name>
		<bndbox>
			<xmin>216</xmin>
			<ymin>347</ymin>
			<xmax>260</xmax>
			<ymax>456</ymax>
		</bndbox>
	</object>
	<object>
		<name>62750</name>
		<bndbox>
			<xmin>190</xmin>
			<ymin>351</ymin>
			<xmax>256</xmax>
			<ymax>394</ymax>
		</bndbox>
	</object>
</annotation>