<annotation>
	<filename>2645724661.jpg</filename>
	<size>
		<width>500</width>
		<height>375</height>
		<depth>3</depth>
	</size>
	<object>
		<name>63641</name>
		<bndbox>
			<xmin>211</xmin>
			<ymin>1</ymin>
			<xmax>425</xmax>
			<ymax>375</ymax>
		</bndbox>
	</object>
	<object>
		<name>63642</name>
		<bndbox>
			<xmin>265</xmin>
			<ymin>96</ymin>
			<xmax>416</xmax>
			<ymax>375</ymax>
		</bndbox>
	</object>
	<object>
		<name>63643</name>
		<bndbox>
			<xmin>223</xmin>
			<ymin>237</ymin>
			<xmax>496</xmax>
			<ymax>344</ymax>
		</bndbox>
	</object>
	<object>
		<name>63644</name>
		<bndbox>
			<xmin>47</xmin>
			<ymin>176</ymin>
			<xmax>118</xmax>
			<ymax>244</ymax>
		</bndbox>
	</object>
</annotation>