<annotation>
	<filename>2755314937.jpg</filename>
	<size>
		<width>333</width>
		<height>500</height>
		<depth>3</depth>
	</size>
	<object>
		<name>70805</name>
		<bndbox>
			<xmin>13</xmin>
			<ymin>337</ymin>
			<xmax>333</xmax>
			<ymax>500</ymax>
		</bndbox>
	</object>
	<object>
		<name>70804</name>
		<bndbox>
			<xmin>11</xmin>
			<ymin>34</ymin>
			<xmax>333</xmax>
			<ymax>500</ymax>
		</bndbox>
	</object>
	<object>
		<name>70806</name>
		<bndbox>
			<xmin>137</xmin>
			<ymin>291</ymin>
			<xmax>198</xmax>
			<ymax>371</ymax>
		</bndbox>
	</object>
	<object>
		<name>70807</name>
		<scene>0</scene>
		<nobndbox>1</nobndbox>
	</object>
</annotation>