<annotation>
	<filename>2867174889.jpg</filename>
	<size>
		<width>375</width>
		<height>500</height>
		<depth>3</depth>
	</size>
	<object>
		<name>77764</name>
		<bndbox>
			<xmin>172</xmin>
			<ymin>92</ymin>
			<xmax>342</xmax>
			<ymax>499</ymax>
		</bndbox>
	</object>
	<object>
		<name>77765</name>
		<bndbox>
			<xmin>215</xmin>
			<ymin>157</ymin>
			<xmax>338</xmax>
			<ymax>476</ymax>
		</bndbox>
	</object>
	<object>
		<name>77766</name>
		<bndbox>
			<xmin>81</xmin>
			<ymin>2</ymin>
			<xmax>240</xmax>
			<ymax>374</ymax>
		</bndbox>
	</object>
	<object>
		<name>77772</name>
		<bndbox>
			<xmin>175</xmin>
			<ymin>212</ymin>
			<xmax>274</xmax>
			<ymax>254</ymax>
		</bndbox>
	</object>
	<object>
		<name>77769</name>
		<scene>0</scene>
		<nobndbox>1</nobndbox>
	</object>
	<object>
		<name>77770</name>
		<scene>0</scene>
		<nobndbox>1</nobndbox>
	</object>
	<object>
		<name>77773</name>
		<scene>0</scene>
		<nobndbox>1</nobndbox>
	</object>
</annotation>