<annotation>
	<filename>3178005751.jpg</filename>
	<size>
		<width>375</width>
		<height>500</height>
		<depth>3</depth>
	</size>
	<object>
		<name>98578</name>
		<bndbox>
			<xmin>110</xmin>
			<ymin>66</ymin>
			<xmax>336</xmax>
			<ymax>500</ymax>
		</bndbox>
	</object>
	<object>
		<name>98579</name>
		<bndbox>
			<xmin>19</xmin>
			<ymin>14</ymin>
			<xmax>204</xmax>
			<ymax>436</ymax>
		</bndbox>
	</object>
	<object>
		<name>98584</name>
		<bndbox>
			<xmin>172</xmin>
			<ymin>113</ymin>
			<xmax>340</xmax>
			<ymax>316</ymax>
		</bndbox>
	</object>
	<object>
		<name>98580</name>
		<bndbox>
			<xmin>1</xmin>
			<ymin>156</ymin>
			<xmax>374</xmax>
			<ymax>500</ymax>
		</bndbox>
	</object>
	<object>
		<name>98585</name>
		<bndbox>
			<xmin>4</xmin>
			<ymin>122</ymin>
			<xmax>374</xmax>
			<ymax>456</ymax>
		</bndbox>
	</object>
	<object>
		<name>98583</name>
		<bndbox>
			<xmin>55</xmin>
			<ymin>83</ymin>
			<xmax>203</xmax>
			<ymax>256</ymax>
		</bndbox>
	</object>
	<object>
		<name>98582</name>
		<bndbox>
			<xmin>31</xmin>
			<ymin>194</ymin>
			<xmax>156</xmax>
			<ymax>399</ymax>
		</bndbox>
	</object>
	<object>
		<name>98582</name>
		<bndbox>
			<xmin>121</xmin>
			<ymin>259</ymin>
			<xmax>259</xmax>
			<ymax>460</ymax>
		</bndbox>
	</object>
	<object>
		<name>98581</name>
		<bndbox>
			<xmin>1</xmin>
			<ymin>1</ymin>
			<xmax>375</xmax>
			<ymax>231</ymax>
		</bndbox>
	</object>
	<object>
		<name>98586</name>
		<scene>1</scene>
		<nobndbox>1</nobndbox>
	</object>
	<object>
		<name>98587</name>
		<scene>0</scene>
		<nobndbox>1</nobndbox>
	</object>
</annotation>