<annotation>
	<filename>3182405529.jpg</filename>
	<size>
		<width>500</width>
		<height>333</height>
		<depth>3</depth>
	</size>
	<object>
		<name>99001</name>
		<bndbox>
			<xmin>173</xmin>
			<ymin>37</ymin>
			<xmax>290</xmax>
			<ymax>294</ymax>
		</bndbox>
	</object>
	<object>
		<name>99003</name>
		<bndbox>
			<xmin>203</xmin>
			<ymin>60</ymin>
			<xmax>237</xmax>
			<ymax>87</ymax>
		</bndbox>
	</object>
	<object>
		<name>99004</name>
		<bndbox>
			<xmin>163</xmin>
			<ymin>142</ymin>
			<xmax>300</xmax>
			<ymax>304</ymax>
		</bndbox>
	</object>
	<object>
		<name>99005</name>
		<bndbox>
			<xmin>196</xmin>
			<ymin>38</ymin>
			<xmax>244</xmax>
			<ymax>88</ymax>
		</bndbox>
	</object>
	<object>
		<name>99006</name>
		<bndbox>
			<xmin>161</xmin>
			<ymin>38</ymin>
			<xmax>301</xmax>
			<ymax>309</ymax>
		</bndbox>
	</object>
	<object>
		<name>99002</name>
		<scene>0</scene>
		<nobndbox>1</nobndbox>
	</object>
</annotation>