<annotation>
	<filename>3266306177.jpg</filename>
	<size>
		<width>500</width>
		<height>335</height>
		<depth>3</depth>
	</size>
	<object>
		<name>105633</name>
		<name>105634</name>
		<bndbox>
			<xmin>149</xmin>
			<ymin>104</ymin>
			<xmax>416</xmax>
			<ymax>294</ymax>
		</bndbox>
	</object>
	<object>
		<name>105634</name>
		<name>105637</name>
		<bndbox>
			<xmin>189</xmin>
			<ymin>180</ymin>
			<xmax>276</xmax>
			<ymax>267</ymax>
		</bndbox>
	</object>
	<object>
		<name>105635</name>
		<bndbox>
			<xmin>180</xmin>
			<ymin>174</ymin>
			<xmax>282</xmax>
			<ymax>269</ymax>
		</bndbox>
	</object>
	<object>
		<name>105636</name>
		<scene>0</scene>
		<nobndbox>1</nobndbox>
	</object>
</annotation>