<annotation>
	<filename>3710607005.jpg</filename>
	<size>
		<width>500</width>
		<height>375</height>
		<depth>3</depth>
	</size>
	<object>
		<name>138534</name>
		<bndbox>
			<xmin>234</xmin>
			<ymin>58</ymin>
			<xmax>355</xmax>
			<ymax>350</ymax>
		</bndbox>
	</object>
	<object>
		<name>138535</name>
		<bndbox>
			<xmin>193</xmin>
			<ymin>187</ymin>
			<xmax>410</xmax>
			<ymax>340</ymax>
		</bndbox>
	</object>
	<object>
		<name>138536</name>
		<name>138540</name>
		<bndbox>
			<xmin>233</xmin>
			<ymin>99</ymin>
			<xmax>328</xmax>
			<ymax>205</ymax>
		</bndbox>
	</object>
	<object>
		<name>138537</name>
		<name>138540</name>
		<bndbox>
			<xmin>234</xmin>
			<ymin>181</ymin>
			<xmax>370</xmax>
			<ymax>340</ymax>
		</bndbox>
	</object>
	<object>
		<name>138539</name>
		<bndbox>
			<xmin>282</xmin>
			<ymin>69</ymin>
			<xmax>316</xmax>
			<ymax>77</ymax>
		</bndbox>
	</object>
	<object>
		<name>138543</name>
		<bndbox>
			<xmin>300</xmin>
			<ymin>80</ymin>
			<xmax>320</xmax>
			<ymax>107</ymax>
		</bndbox>
	</object>
	<object>
		<name>138543</name>
		<bndbox>
			<xmin>302</xmin>
			<ymin>91</ymin>
			<xmax>319</xmax>
			<ymax>112</ymax>
		</bndbox>
	</object>
	<object>
		<name>138544</name>
		<bndbox>
			<xmin>307</xmin>
			<ymin>84</ymin>
			<xmax>320</xmax>
			<ymax>98</ymax>
		</bndbox>
	</object>
	<object>
		<name>138541</name>
		<scene>0</scene>
		<nobndbox>1</nobndbox>
	</object>
	<object>
		<name>138542</name>
		<scene>0</scene>
		<nobndbox>1</nobndbox>
	</object>
</annotation>