<annotation>
	<filename>4001914227.jpg</filename>
	<size>
		<width>500</width>
		<height>338</height>
		<depth>3</depth>
	</size>
	<object>
		<name>151515</name>
		<bndbox>
			<xmin>303</xmin>
			<ymin>87</ymin>
			<xmax>426</xmax>
			<ymax>268</ymax>
		</bndbox>
	</object>
	<object>
		<name>151516</name>
		<bndbox>
			<xmin>2</xmin>
			<ymin>149</ymin>
			<xmax>500</xmax>
			<ymax>338</ymax>
		</bndbox>
	</object>
	<object>
		<name>151517</name>
		<bndbox>
			<xmin>1</xmin>
			<ymin>62</ymin>
			<xmax>499</xmax>
			<ymax>338</ymax>
		</bndbox>
	</object>
	<object>
		<name>151518</name>
		<bndbox>
			<xmin>142</xmin>
			<ymin>160</ymin>
			<xmax>404</xmax>
			<ymax>316</ymax>
		</bndbox>
	</object>
	<object>
		<name>151519</name>
		<bndbox>
			<xmin>329</xmin>
			<ymin>107</ymin>
			<xmax>414</xmax>
			<ymax>190</ymax>
		</bndbox>
	</object>
	<object>
		<name>151521</name>
		<scene>0</scene>
		<nobndbox>1</nobndbox>
	</object>
	<object>
		<name>151522</name>
		<scene>0</scene>
		<nobndbox>1</nobndbox>
	</object>
	<object>
		<name>151523</name>
		<scene>0</scene>
		<nobndbox>1</nobndbox>
	</object>
</annotation>