<annotation>
	<filename>4088620453.jpg</filename>
	<size>
		<width>500</width>
		<height>333</height>
		<depth>3</depth>
	</size>
	<object>
		<name>154812</name>
		<bndbox>
			<xmin>2</xmin>
			<ymin>1</ymin>
			<xmax>300</xmax>
			<ymax>333</ymax>
		</bndbox>
	</object>
	<object>
		<name>154813</name>
		<bndbox>
			<xmin>255</xmin>
			<ymin>286</ymin>
			<xmax>289</xmax>
			<ymax>314</ymax>
		</bndbox>
	</object>
	<object>
		<name>154814</name>
		<bndbox>
			<xmin>255</xmin>
			<ymin>284</ymin>
			<xmax>282</xmax>
			<ymax>306</ymax>
		</bndbox>
	</object>
	<object>
		<name>154815</name>
		<bndbox>
			<xmin>255</xmin>
			<ymin>277</ymin>
			<xmax>291</xmax>
			<ymax>316</ymax>
		</bndbox>
	</object>
	<object>
		<name>154816</name>
		<bndbox>
			<xmin>356</xmin>
			<ymin>35</ymin>
			<xmax>500</xmax>
			<ymax>333</ymax>
		</bndbox>
	</object>
	<object>
		<name>154817</name>
		<bndbox>
			<xmin>357</xmin>
			<ymin>166</ymin>
			<xmax>388</xmax>
			<ymax>257</ymax>
		</bndbox>
	</object>
	<object>
		<name>154818</name>
		<bndbox>
			<xmin>378</xmin>
			<ymin>89</ymin>
			<xmax>478</xmax>
			<ymax>129</ymax>
		</bndbox>
	</object>
	<object>
		<name>154821</name>
		<bndbox>
			<xmin>383</xmin>
			<ymin>96</ymin>
			<xmax>483</xmax>
			<ymax>129</ymax>
		</bndbox>
	</object>
	<object>
		<name>154822</name>
		<name>154823</name>
		<bndbox>
			<xmin>203</xmin>
			<ymin>271</ymin>
			<xmax>298</xmax>
			<ymax>332</ymax>
		</bndbox>
	</object>
	<object>
		<name>154823</name>
		<bndbox>
			<xmin>354</xmin>
			<ymin>185</ymin>
			<xmax>411</xmax>
			<ymax>250</ymax>
		</bndbox>
	</object>
	<object>
		<name>154820</name>
		<scene>0</scene>
		<nobndbox>1</nobndbox>
	</object>
</annotation>