<annotation>
	<filename>4145119743.jpg</filename>
	<size>
		<width>500</width>
		<height>375</height>
		<depth>3</depth>
	</size>
	<object>
		<name>156836</name>
		<name>156838</name>
		<bndbox>
			<xmin>131</xmin>
			<ymin>101</ymin>
			<xmax>281</xmax>
			<ymax>284</ymax>
		</bndbox>
	</object>
	<object>
		<name>156838</name>
		<bndbox>
			<xmin>237</xmin>
			<ymin>1</ymin>
			<xmax>500</xmax>
			<ymax>375</ymax>
		</bndbox>
	</object>
	<object>
		<name>156839</name>
		<bndbox>
			<xmin>169</xmin>
			<ymin>232</ymin>
			<xmax>205</xmax>
			<ymax>258</ymax>
		</bndbox>
	</object>
	<object>
		<name>156841</name>
		<bndbox>
			<xmin>1</xmin>
			<ymin>1</ymin>
			<xmax>496</xmax>
			<ymax>374</ymax>
		</bndbox>
	</object>
	<object>
		<name>156843</name>
		<bndbox>
			<xmin>131</xmin>
			<ymin>141</ymin>
			<xmax>281</xmax>
			<ymax>283</ymax>
		</bndbox>
	</object>
	<object>
		<name>156837</name>
		<scene>0</scene>
		<nobndbox>1</nobndbox>
	</object>
	<object>
		<name>156842</name>
		<scene>0</scene>
		<nobndbox>1</nobndbox>
	</object>
</annotation>