<annotation>
	<filename>4433557295.jpg</filename>
	<size>
		<width>500</width>
		<height>336</height>
		<depth>3</depth>
	</size>
	<object>
		<name>167623</name>
		<bndbox>
			<xmin>12</xmin>
			<ymin>7</ymin>
			<xmax>268</xmax>
			<ymax>336</ymax>
		</bndbox>
	</object>
	<object>
		<name>167625</name>
		<bndbox>
			<xmin>11</xmin>
			<ymin>11</ymin>
			<xmax>63</xmax>
			<ymax>69</ymax>
		</bndbox>
	</object>
	<object>
		<name>167626</name>
		<bndbox>
			<xmin>25</xmin>
			<ymin>50</ymin>
			<xmax>178</xmax>
			<ymax>232</ymax>
		</bndbox>
	</object>
	<object>
		<name>167627</name>
		<bndbox>
			<xmin>163</xmin>
			<ymin>234</ymin>
			<xmax>202</xmax>
			<ymax>277</ymax>
		</bndbox>
	</object>
	<object>
		<name>167628</name>
		<bndbox>
			<xmin>146</xmin>
			<ymin>151</ymin>
			<xmax>499</xmax>
			<ymax>329</ymax>
		</bndbox>
	</object>
	<object>
		<name>167628</name>
		<bndbox>
			<xmin>184</xmin>
			<ymin>312</ymin>
			<xmax>261</xmax>
			<ymax>336</ymax>
		</bndbox>
	</object>
	<object>
		<name>167629</name>
		<bndbox>
			<xmin>255</xmin>
			<ymin>54</ymin>
			<xmax>500</xmax>
			<ymax>335</ymax>
		</bndbox>
	</object>
	<object>
		<name>167630</name>
		<bndbox>
			<xmin>219</xmin>
			<ymin>17</ymin>
			<xmax>356</xmax>
			<ymax>164</ymax>
		</bndbox>
	</object>
	<object>
		<name>167630</name>
		<bndbox>
			<xmin>24</xmin>
			<ymin>203</ymin>
			<xmax>73</xmax>
			<ymax>265</ymax>
		</bndbox>
	</object>
	<object>
		<name>167631</name>
		<bndbox>
			<xmin>358</xmin>
			<ymin>2</ymin>
			<xmax>500</xmax>
			<ymax>132</ymax>
		</bndbox>
	</object>
	<object>
		<name>167632</name>
		<bndbox>
			<xmin>3</xmin>
			<ymin>1</ymin>
			<xmax>420</xmax>
			<ymax>303</ymax>
		</bndbox>
	</object>
	<object>
		<name>167624</name>
		<scene>0</scene>
		<nobndbox>1</nobndbox>
	</object>
</annotation>