<annotation>
	<filename>4589054322.jpg</filename>
	<size>
		<width>500</width>
		<height>333</height>
		<depth>3</depth>
	</size>
	<object>
		<name>180894</name>
		<bndbox>
			<xmin>75</xmin>
			<ymin>106</ymin>
			<xmax>278</xmax>
			<ymax>329</ymax>
		</bndbox>
	</object>
	<object>
		<name>180898</name>
		<bndbox>
			<xmin>157</xmin>
			<ymin>123</ymin>
			<xmax>255</xmax>
			<ymax>269</ymax>
		</bndbox>
	</object>
	<object>
		<name>180896</name>
		<bndbox>
			<xmin>67</xmin>
			<ymin>186</ymin>
			<xmax>321</xmax>
			<ymax>309</ymax>
		</bndbox>
	</object>
	<object>
		<name>180897</name>
		<bndbox>
			<xmin>63</xmin>
			<ymin>135</ymin>
			<xmax>255</xmax>
			<ymax>316</ymax>
		</bndbox>
	</object>
	<object>
		<name>180899</name>
		<bndbox>
			<xmin>2</xmin>
			<ymin>1</ymin>
			<xmax>499</xmax>
			<ymax>314</ymax>
		</bndbox>
	</object>
	<object>
		<name>180895</name>
		<bndbox>
			<xmin>64</xmin>
			<ymin>47</ymin>
			<xmax>203</xmax>
			<ymax>96</ymax>
		</bndbox>
	</object>
	<object>
		<name>180900</name>
		<bndbox>
			<xmin>250</xmin>
			<ymin>17</ymin>
			<xmax>490</xmax>
			<ymax>327</ymax>
		</bndbox>
	</object>
	<object>
		<name>180901</name>
		<scene>1</scene>
		<nobndbox>1</nobndbox>
	</object>
</annotation>