<annotation>
	<filename>4764136953.jpg</filename>
	<size>
		<width>500</width>
		<height>345</height>
		<depth>3</depth>
	</size>
	<object>
		<name>200556</name>
		<name>200559</name>
		<bndbox>
			<xmin>94</xmin>
			<ymin>52</ymin>
			<xmax>260</xmax>
			<ymax>345</ymax>
		</bndbox>
	</object>
	<object>
		<name>200556</name>
		<name>200557</name>
		<bndbox>
			<xmin>238</xmin>
			<ymin>3</ymin>
			<xmax>420</xmax>
			<ymax>271</ymax>
		</bndbox>
	</object>
	<object>
		<name>200562</name>
		<bndbox>
			<xmin>6</xmin>
			<ymin>1</ymin>
			<xmax>500</xmax>
			<ymax>343</ymax>
		</bndbox>
	</object>
	<object>
		<name>200564</name>
		<bndbox>
			<xmin>38</xmin>
			<ymin>97</ymin>
			<xmax>94</xmax>
			<ymax>142</ymax>
		</bndbox>
	</object>
	<object>
		<name>200565</name>
		<bndbox>
			<xmin>47</xmin>
			<ymin>119</ymin>
			<xmax>71</xmax>
			<ymax>345</ymax>
		</bndbox>
	</object>
	<object>
		<name>200566</name>
		<bndbox>
			<xmin>173</xmin>
			<ymin>204</ymin>
			<xmax>273</xmax>
			<ymax>300</ymax>
		</bndbox>
	</object>
	<object>
		<name>200568</name>
		<bndbox>
			<xmin>112</xmin>
			<ymin>129</ymin>
			<xmax>241</xmax>
			<ymax>345</ymax>
		</bndbox>
	</object>
	<object>
		<name>200569</name>
		<bndbox>
			<xmin>141</xmin>
			<ymin>74</ymin>
			<xmax>206</xmax>
			<ymax>101</ymax>
		</bndbox>
	</object>
	<object>
		<name>200569</name>
		<bndbox>
			<xmin>140</xmin>
			<ymin>72</ymin>
			<xmax>205</xmax>
			<ymax>106</ymax>
		</bndbox>
	</object>
	<object>
		<name>200558</name>
		<scene>0</scene>
		<nobndbox>1</nobndbox>
	</object>
	<object>
		<name>200567</name>
		<scene>0</scene>
		<nobndbox>1</nobndbox>
	</object>
</annotation>