<annotation>
	<filename>4799330472.jpg</filename>
	<size>
		<width>500</width>
		<height>333</height>
		<depth>3</depth>
	</size>
	<object>
		<name>203902</name>
		<name>203905</name>
		<bndbox>
			<xmin>229</xmin>
			<ymin>200</ymin>
			<xmax>295</xmax>
			<ymax>333</ymax>
		</bndbox>
	</object>
	<object>
		<name>203904</name>
		<bndbox>
			<xmin>230</xmin>
			<ymin>231</ymin>
			<xmax>294</xmax>
			<ymax>331</ymax>
		</bndbox>
	</object>
	<object>
		<name>203905</name>
		<bndbox>
			<xmin>342</xmin>
			<ymin>197</ymin>
			<xmax>403</xmax>
			<ymax>330</ymax>
		</bndbox>
	</object>
	<object>
		<name>203905</name>
		<bndbox>
			<xmin>68</xmin>
			<ymin>192</ymin>
			<xmax>138</xmax>
			<ymax>292</ymax>
		</bndbox>
	</object>
	<object>
		<name>203905</name>
		<bndbox>
			<xmin>2</xmin>
			<ymin>186</ymin>
			<xmax>82</xmax>
			<ymax>288</ymax>
		</bndbox>
	</object>
	<object>
		<name>203903</name>
		<scene>0</scene>
		<nobndbox>1</nobndbox>
	</object>
	<object>
		<name>203906</name>
		<scene>0</scene>
		<nobndbox>1</nobndbox>
	</object>
	<object>
		<name>203907</name>
		<scene>0</scene>
		<nobndbox>1</nobndbox>
	</object>
	<object>
		<name>203908</name>
		<scene>0</scene>
		<nobndbox>1</nobndbox>
	</object>
</annotation>