<annotation>
	<filename>4878658676.jpg</filename>
	<size>
		<width>500</width>
		<height>333</height>
		<depth>3</depth>
	</size>
	<object>
		<name>214153</name>
		<bndbox>
			<xmin>205</xmin>
			<ymin>71</ymin>
			<xmax>327</xmax>
			<ymax>289</ymax>
		</bndbox>
	</object>
	<object>
		<name>214154</name>
		<bndbox>
			<xmin>170</xmin>
			<ymin>160</ymin>
			<xmax>340</xmax>
			<ymax>309</ymax>
		</bndbox>
	</object>
	<object>
		<name>214155</name>
		<bndbox>
			<xmin>290</xmin>
			<ymin>74</ymin>
			<xmax>351</xmax>
			<ymax>174</ymax>
		</bndbox>
	</object>
	<object>
		<name>214156</name>
		<bndbox>
			<xmin>251</xmin>
			<ymin>100</ymin>
			<xmax>325</xmax>
			<ymax>184</ymax>
		</bndbox>
	</object>
	<object>
		<name>214157</name>
		<bndbox>
			<xmin>218</xmin>
			<ymin>242</ymin>
			<xmax>312</xmax>
			<ymax>286</ymax>
		</bndbox>
	</object>
	<object>
		<name>214158</name>
		<bndbox>
			<xmin>272</xmin>
			<ymin>72</ymin>
			<xmax>288</xmax>
			<ymax>103</ymax>
		</bndbox>
	</object>
	<object>
		<name>214159</name>
		<bndbox>
			<xmin>235</xmin>
			<ymin>159</ymin>
			<xmax>322</xmax>
			<ymax>222</ymax>
		</bndbox>
	</object>
	<object>
		<name>214160</name>
		<scene>0</scene>
		<nobndbox>1</nobndbox>
	</object>
</annotation>