<annotation>
	<filename>4899353764.jpg</filename>
	<size>
		<width>500</width>
		<height>402</height>
		<depth>3</depth>
	</size>
	<object>
		<name>216511</name>
		<bndbox>
			<xmin>1</xmin>
			<ymin>32</ymin>
			<xmax>163</xmax>
			<ymax>402</ymax>
		</bndbox>
	</object>
	<object>
		<name>216512</name>
		<bndbox>
			<xmin>120</xmin>
			<ymin>126</ymin>
			<xmax>500</xmax>
			<ymax>401</ymax>
		</bndbox>
	</object>
	<object>
		<name>216513</name>
		<name>216517</name>
		<bndbox>
			<xmin>209</xmin>
			<ymin>174</ymin>
			<xmax>308</xmax>
			<ymax>400</ymax>
		</bndbox>
	</object>
	<object>
		<name>216513</name>
		<name>216516</name>
		<bndbox>
			<xmin>276</xmin>
			<ymin>150</ymin>
			<xmax>427</xmax>
			<ymax>401</ymax>
		</bndbox>
	</object>
	<object>
		<name>216514</name>
		<name>216518</name>
		<bndbox>
			<xmin>218</xmin>
			<ymin>223</ymin>
			<xmax>308</xmax>
			<ymax>322</ymax>
		</bndbox>
	</object>
	<object>
		<name>216515</name>
		<bndbox>
			<xmin>249</xmin>
			<ymin>190</ymin>
			<xmax>282</xmax>
			<ymax>208</ymax>
		</bndbox>
	</object>
	<object>
		<name>216518</name>
		<name>216519</name>
		<bndbox>
			<xmin>284</xmin>
			<ymin>227</ymin>
			<xmax>429</xmax>
			<ymax>402</ymax>
		</bndbox>
	</object>
	<object>
		<name>216520</name>
		<bndbox>
			<xmin>139</xmin>
			<ymin>259</ymin>
			<xmax>239</xmax>
			<ymax>402</ymax>
		</bndbox>
	</object>
	<object>
		<name>216521</name>
		<bndbox>
			<xmin>2</xmin>
			<ymin>139</ymin>
			<xmax>139</xmax>
			<ymax>402</ymax>
		</bndbox>
	</object>
	<object>
		<name>216527</name>
		<bndbox>
			<xmin>4</xmin>
			<ymin>1</ymin>
			<xmax>500</xmax>
			<ymax>400</ymax>
		</bndbox>
	</object>
	<object>
		<name>216523</name>
		<scene>0</scene>
		<nobndbox>1</nobndbox>
	</object>
</annotation>