<annotation>
	<filename>4928593125.jpg</filename>
	<size>
		<width>500</width>
		<height>375</height>
		<depth>3</depth>
	</size>
	<object>
		<name>219257</name>
		<name>219262</name>
		<bndbox>
			<xmin>95</xmin>
			<ymin>114</ymin>
			<xmax>178</xmax>
			<ymax>308</ymax>
		</bndbox>
	</object>
	<object>
		<name>219257</name>
		<name>219260</name>
		<name>219265</name>
		<bndbox>
			<xmin>280</xmin>
			<ymin>95</ymin>
			<xmax>354</xmax>
			<ymax>242</ymax>
		</bndbox>
	</object>
	<object>
		<name>219257</name>
		<bndbox>
			<xmin>214</xmin>
			<ymin>91</ymin>
			<xmax>286</xmax>
			<ymax>265</ymax>
		</bndbox>
	</object>
	<object>
		<name>219258</name>
		<bndbox>
			<xmin>5</xmin>
			<ymin>87</ymin>
			<xmax>499</xmax>
			<ymax>370</ymax>
		</bndbox>
	</object>
	<object>
		<name>219259</name>
		<bndbox>
			<xmin>235</xmin>
			<ymin>48</ymin>
			<xmax>368</xmax>
			<ymax>127</ymax>
		</bndbox>
	</object>
	<object>
		<name>219263</name>
		<bndbox>
			<xmin>109</xmin>
			<ymin>145</ymin>
			<xmax>149</xmax>
			<ymax>197</ymax>
		</bndbox>
	</object>
	<object>
		<name>219265</name>
		<bndbox>
			<xmin>219</xmin>
			<ymin>90</ymin>
			<xmax>298</xmax>
			<ymax>261</ymax>
		</bndbox>
	</object>
	<object>
		<name>219261</name>
		<scene>0</scene>
		<nobndbox>1</nobndbox>
	</object>
	<object>
		<name>219264</name>
		<scene>0</scene>
		<nobndbox>1</nobndbox>
	</object>
</annotation>