<annotation>
	<filename>4952694407.jpg</filename>
	<size>
		<width>500</width>
		<height>374</height>
		<depth>3</depth>
	</size>
	<object>
		<name>222673</name>
		<name>222675</name>
		<name>222677</name>
		<bndbox>
			<xmin>11</xmin>
			<ymin>82</ymin>
			<xmax>77</xmax>
			<ymax>165</ymax>
		</bndbox>
	</object>
	<object>
		<name>222673</name>
		<name>222675</name>
		<name>222677</name>
		<bndbox>
			<xmin>138</xmin>
			<ymin>83</ymin>
			<xmax>190</xmax>
			<ymax>165</ymax>
		</bndbox>
	</object>
	<object>
		<name>222673</name>
		<name>222675</name>
		<name>222677</name>
		<bndbox>
			<xmin>71</xmin>
			<ymin>60</ymin>
			<xmax>146</xmax>
			<ymax>167</ymax>
		</bndbox>
	</object>
	<object>
		<name>222673</name>
		<bndbox>
			<xmin>268</xmin>
			<ymin>98</ymin>
			<xmax>295</xmax>
			<ymax>165</ymax>
		</bndbox>
	</object>
	<object>
		<name>222673</name>
		<bndbox>
			<xmin>178</xmin>
			<ymin>97</ymin>
			<xmax>220</xmax>
			<ymax>169</ymax>
		</bndbox>
	</object>
	<object>
		<name>222673</name>
		<bndbox>
			<xmin>207</xmin>
			<ymin>88</ymin>
			<xmax>238</xmax>
			<ymax>129</ymax>
		</bndbox>
	</object>
	<object>
		<name>222673</name>
		<name>222675</name>
		<bndbox>
			<xmin>216</xmin>
			<ymin>84</ymin>
			<xmax>265</xmax>
			<ymax>165</ymax>
		</bndbox>
	</object>
	<object>
		<name>222673</name>
		<name>222676</name>
		<name>222677</name>
		<bndbox>
			<xmin>306</xmin>
			<ymin>82</ymin>
			<xmax>370</xmax>
			<ymax>233</ymax>
		</bndbox>
	</object>
	<object>
		<name>222675</name>
		<name>222677</name>
		<bndbox>
			<xmin>261</xmin>
			<ymin>78</ymin>
			<xmax>311</xmax>
			<ymax>166</ymax>
		</bndbox>
	</object>
	<object>
		<name>222675</name>
		<name>222677</name>
		<bndbox>
			<xmin>185</xmin>
			<ymin>99</ymin>
			<xmax>223</xmax>
			<ymax>166</ymax>
		</bndbox>
	</object>
	<object>
		<name>222677</name>
		<bndbox>
			<xmin>206</xmin>
			<ymin>91</ymin>
			<xmax>240</xmax>
			<ymax>156</ymax>
		</bndbox>
	</object>
	<object>
		<name>222677</name>
		<bndbox>
			<xmin>243</xmin>
			<ymin>89</ymin>
			<xmax>269</xmax>
			<ymax>164</ymax>
		</bndbox>
	</object>
	<object>
		<name>222678</name>
		<bndbox>
			<xmin>309</xmin>
			<ymin>99</ymin>
			<xmax>353</xmax>
			<ymax>144</ymax>
		</bndbox>
	</object>
	<object>
		<name>222679</name>
		<bndbox>
			<xmin>303</xmin>
			<ymin>131</ymin>
			<xmax>342</xmax>
			<ymax>170</ymax>
		</bndbox>
	</object>
	<object>
		<name>222680</name>
		<name>222683</name>
		<bndbox>
			<xmin>69</xmin>
			<ymin>87</ymin>
			<xmax>144</xmax>
			<ymax>169</ymax>
		</bndbox>
	</object>
	<object>
		<name>222680</name>
		<bndbox>
			<xmin>8</xmin>
			<ymin>109</ymin>
			<xmax>76</xmax>
			<ymax>168</ymax>
		</bndbox>
	</object>
	<object>
		<name>222680</name>
		<bndbox>
			<xmin>136</xmin>
			<ymin>102</ymin>
			<xmax>183</xmax>
			<ymax>163</ymax>
		</bndbox>
	</object>
	<object>
		<name>222680</name>
		<bndbox>
			<xmin>179</xmin>
			<ymin>124</ymin>
			<xmax>224</xmax>
			<ymax>162</ymax>
		</bndbox>
	</object>
	<object>
		<name>222680</name>
		<bndbox>
			<xmin>268</xmin>
			<ymin>101</ymin>
			<xmax>292</xmax>
			<ymax>148</ymax>
		</bndbox>
	</object>
	<object>
		<name>222680</name>
		<bndbox>
			<xmin>219</xmin>
			<ymin>103</ymin>
			<xmax>265</xmax>
			<ymax>166</ymax>
		</bndbox>
	</object>
	<object>
		<name>222681</name>
		<bndbox>
			<xmin>346</xmin>
			<ymin>90</ymin>
			<xmax>358</xmax>
			<ymax>107</ymax>
		</bndbox>
	</object>
	<object>
		<name>222686</name>
		<bndbox>
			<xmin>3</xmin>
			<ymin>162</ymin>
			<xmax>500</xmax>
			<ymax>274</ymax>
		</bndbox>
	</object>
	<object>
		<name>222674</name>
		<scene>0</scene>
		<nobndbox>1</nobndbox>
	</object>
	<object>
		<name>222682</name>
		<scene>0</scene>
		<nobndbox>1</nobndbox>
	</object>
</annotation>