<annotation>
	<filename>512309690.jpg</filename>
	<size>
		<width>333</width>
		<height>500</height>
		<depth>3</depth>
	</size>
	<object>
		<name>229422</name>
		<bndbox>
			<xmin>42</xmin>
			<ymin>65</ymin>
			<xmax>333</xmax>
			<ymax>500</ymax>
		</bndbox>
	</object>
	<object>
		<name>229423</name>
		<bndbox>
			<xmin>4</xmin>
			<ymin>279</ymin>
			<xmax>218</xmax>
			<ymax>500</ymax>
		</bndbox>
	</object>
	<object>
		<name>229424</name>
		<bndbox>
			<xmin>104</xmin>
			<ymin>227</ymin>
			<xmax>333</xmax>
			<ymax>421</ymax>
		</bndbox>
	</object>
	<object>
		<name>229425</name>
		<bndbox>
			<xmin>47</xmin>
			<ymin>189</ymin>
			<xmax>332</xmax>
			<ymax>500</ymax>
		</bndbox>
	</object>
	<object>
		<name>229426</name>
		<bndbox>
			<xmin>1</xmin>
			<ymin>1</ymin>
			<xmax>332</xmax>
			<ymax>500</ymax>
		</bndbox>
	</object>
	<object>
		<name>229427</name>
		<bndbox>
			<xmin>187</xmin>
			<ymin>225</ymin>
			<xmax>313</xmax>
			<ymax>419</ymax>
		</bndbox>
	</object>
	<object>
		<name>229428</name>
		<bndbox>
			<xmin>101</xmin>
			<ymin>301</ymin>
			<xmax>333</xmax>
			<ymax>420</ymax>
		</bndbox>
	</object>
</annotation>