<annotation>
	<filename>593244695.jpg</filename>
	<size>
		<width>500</width>
		<height>333</height>
		<depth>3</depth>
	</size>
	<object>
		<name>245672</name>
		<bndbox>
			<xmin>220</xmin>
			<ymin>185</ymin>
			<xmax>262</xmax>
			<ymax>262</ymax>
		</bndbox>
	</object>
	<object>
		<name>245674</name>
		<bndbox>
			<xmin>216</xmin>
			<ymin>177</ymin>
			<xmax>312</xmax>
			<ymax>267</ymax>
		</bndbox>
	</object>
	<object>
		<name>245675</name>
		<bndbox>
			<xmin>176</xmin>
			<ymin>2</ymin>
			<xmax>254</xmax>
			<ymax>184</ymax>
		</bndbox>
	</object>
	<object>
		<name>245676</name>
		<bndbox>
			<xmin>218</xmin>
			<ymin>193</ymin>
			<xmax>263</xmax>
			<ymax>266</ymax>
		</bndbox>
	</object>
	<object>
		<name>245673</name>
		<scene>0</scene>
		<nobndbox>1</nobndbox>
	</object>
</annotation>