<annotation>
	<filename>5961657980.jpg</filename>
	<size>
		<width>500</width>
		<height>375</height>
		<depth>3</depth>
	</size>
	<object>
		<name>246052</name>
		<bndbox>
			<xmin>1</xmin>
			<ymin>122</ymin>
			<xmax>500</xmax>
			<ymax>375</ymax>
		</bndbox>
	</object>
	<object>
		<name>246054</name>
		<bndbox>
			<xmin>194</xmin>
			<ymin>215</ymin>
			<xmax>229</xmax>
			<ymax>303</ymax>
		</bndbox>
	</object>
	<object>
		<name>246054</name>
		<bndbox>
			<xmin>94</xmin>
			<ymin>206</ymin>
			<xmax>129</xmax>
			<ymax>290</ymax>
		</bndbox>
	</object>
	<object>
		<name>246054</name>
		<bndbox>
			<xmin>335</xmin>
			<ymin>200</ymin>
			<xmax>366</xmax>
			<ymax>274</ymax>
		</bndbox>
	</object>
	<object>
		<name>246055</name>
		<bndbox>
			<xmin>1</xmin>
			<ymin>236</ymin>
			<xmax>433</xmax>
			<ymax>355</ymax>
		</bndbox>
	</object>
	<object>
		<name>246058</name>
		<bndbox>
			<xmin>4</xmin>
			<ymin>169</ymin>
			<xmax>500</xmax>
			<ymax>373</ymax>
		</bndbox>
	</object>
	<object>
		<name>246059</name>
		<bndbox>
			<xmin>92</xmin>
			<ymin>44</ymin>
			<xmax>374</xmax>
			<ymax>194</ymax>
		</bndbox>
	</object>
	<object>
		<name>246059</name>
		<bndbox>
			<xmin>359</xmin>
			<ymin>1</ymin>
			<xmax>500</xmax>
			<ymax>207</ymax>
		</bndbox>
	</object>
	<object>
		<name>246053</name>
		<scene>0</scene>
		<nobndbox>1</nobndbox>
	</object>
	<object>
		<name>246056</name>
		<scene>0</scene>
		<nobndbox>1</nobndbox>
	</object>
	<object>
		<name>246057</name>
		<scene>0</scene>
		<nobndbox>1</nobndbox>
	</object>
</annotation>