<annotation>
	<filename>6038122264.jpg</filename>
	<size>
		<width>500</width>
		<height>367</height>
		<depth>3</depth>
	</size>
	<object>
		<name>246936</name>
		<bndbox>
			<xmin>294</xmin>
			<ymin>117</ymin>
			<xmax>497</xmax>
			<ymax>363</ymax>
		</bndbox>
	</object>
	<object>
		<name>246937</name>
		<bndbox>
			<xmin>345</xmin>
			<ymin>127</ymin>
			<xmax>422</xmax>
			<ymax>168</ymax>
		</bndbox>
	</object>
	<object>
		<name>246938</name>
		<bndbox>
			<xmin>1</xmin>
			<ymin>2</ymin>
			<xmax>361</xmax>
			<ymax>367</ymax>
		</bndbox>
	</object>
	<object>
		<name>246940</name>
		<bndbox>
			<xmin>276</xmin>
			<ymin>232</ymin>
			<xmax>307</xmax>
			<ymax>288</ymax>
		</bndbox>
	</object>
	<object>
		<name>246941</name>
		<bndbox>
			<xmin>128</xmin>
			<ymin>68</ymin>
			<xmax>498</xmax>
			<ymax>367</ymax>
		</bndbox>
	</object>
	<object>
		<name>246942</name>
		<bndbox>
			<xmin>280</xmin>
			<ymin>225</ymin>
			<xmax>323</xmax>
			<ymax>293</ymax>
		</bndbox>
	</object>
	<object>
		<name>246943</name>
		<bndbox>
			<xmin>301</xmin>
			<ymin>125</ymin>
			<xmax>500</xmax>
			<ymax>366</ymax>
		</bndbox>
	</object>
</annotation>