<annotation>
	<filename>64623852.jpg</filename>
	<size>
		<width>500</width>
		<height>377</height>
		<depth>3</depth>
	</size>
	<object>
		<name>254538</name>
		<bndbox>
			<xmin>203</xmin>
			<ymin>42</ymin>
			<xmax>481</xmax>
			<ymax>377</ymax>
		</bndbox>
	</object>
	<object>
		<name>254539</name>
		<bndbox>
			<xmin>60</xmin>
			<ymin>39</ymin>
			<xmax>479</xmax>
			<ymax>377</ymax>
		</bndbox>
	</object>
	<object>
		<name>254541</name>
		<bndbox>
			<xmin>65</xmin>
			<ymin>73</ymin>
			<xmax>394</xmax>
			<ymax>374</ymax>
		</bndbox>
	</object>
	<object>
		<name>254543</name>
		<bndbox>
			<xmin>71</xmin>
			<ymin>181</ymin>
			<xmax>302</xmax>
			<ymax>377</ymax>
		</bndbox>
	</object>
	<object>
		<name>254543</name>
		<bndbox>
			<xmin>238</xmin>
			<ymin>141</ymin>
			<xmax>464</xmax>
			<ymax>377</ymax>
		</bndbox>
	</object>
	<object>
		<name>254544</name>
		<bndbox>
			<xmin>251</xmin>
			<ymin>116</ymin>
			<xmax>392</xmax>
			<ymax>227</ymax>
		</bndbox>
	</object>
	<object>
		<name>254542</name>
		<scene>0</scene>
		<nobndbox>1</nobndbox>
	</object>
	<object>
		<name>254545</name>
		<scene>0</scene>
		<nobndbox>1</nobndbox>
	</object>
	<object>
		<name>254546</name>
		<scene>0</scene>
		<nobndbox>1</nobndbox>
	</object>
</annotation>