<annotation>
	<filename>6942745583.jpg</filename>
	<size>
		<width>500</width>
		<height>375</height>
		<depth>3</depth>
	</size>
	<object>
		<name>262056</name>
		<bndbox>
			<xmin>26</xmin>
			<ymin>107</ymin>
			<xmax>207</xmax>
			<ymax>374</ymax>
		</bndbox>
	</object>
	<object>
		<name>262057</name>
		<bndbox>
			<xmin>260</xmin>
			<ymin>132</ymin>
			<xmax>479</xmax>
			<ymax>310</ymax>
		</bndbox>
	</object>
	<object>
		<name>262058</name>
		<bndbox>
			<xmin>106</xmin>
			<ymin>234</ymin>
			<xmax>321</xmax>
			<ymax>375</ymax>
		</bndbox>
	</object>
	<object>
		<name>262059</name>
		<bndbox>
			<xmin>97</xmin>
			<ymin>52</ymin>
			<xmax>500</xmax>
			<ymax>375</ymax>
		</bndbox>
	</object>
	<object>
		<name>262060</name>
		<bndbox>
			<xmin>258</xmin>
			<ymin>119</ymin>
			<xmax>497</xmax>
			<ymax>288</ymax>
		</bndbox>
	</object>
	<object>
		<name>262061</name>
		<bndbox>
			<xmin>416</xmin>
			<ymin>220</ymin>
			<xmax>500</xmax>
			<ymax>354</ymax>
		</bndbox>
	</object>
	<object>
		<name>262062</name>
		<bndbox>
			<xmin>41</xmin>
			<ymin>109</ymin>
			<xmax>161</xmax>
			<ymax>223</ymax>
		</bndbox>
	</object>
	<object>
		<name>262063</name>
		<bndbox>
			<xmin>29</xmin>
			<ymin>118</ymin>
			<xmax>121</xmax>
			<ymax>311</ymax>
		</bndbox>
	</object>
</annotation>