<annotation>
	<filename>6948376088.jpg</filename>
	<size>
		<width>500</width>
		<height>197</height>
		<depth>3</depth>
	</size>
	<object>
		<name>262229</name>
		<name>262230</name>
		<name>262232</name>
		<bndbox>
			<xmin>103</xmin>
			<ymin>78</ymin>
			<xmax>201</xmax>
			<ymax>162</ymax>
		</bndbox>
	</object>
	<object>
		<name>262230</name>
		<name>262232</name>
		<name>262233</name>
		<bndbox>
			<xmin>192</xmin>
			<ymin>47</ymin>
			<xmax>278</xmax>
			<ymax>158</ymax>
		</bndbox>
	</object>
	<object>
		<name>262231</name>
		<bndbox>
			<xmin>146</xmin>
			<ymin>127</ymin>
			<xmax>166</xmax>
			<ymax>145</ymax>
		</bndbox>
	</object>
	<object>
		<name>262232</name>
		<bndbox>
			<xmin>437</xmin>
			<ymin>32</ymin>
			<xmax>472</xmax>
			<ymax>121</ymax>
		</bndbox>
	</object>
	<object>
		<name>262232</name>
		<bndbox>
			<xmin>302</xmin>
			<ymin>18</ymin>
			<xmax>347</xmax>
			<ymax>112</ymax>
		</bndbox>
	</object>
	<object>
		<name>262232</name>
		<bndbox>
			<xmin>357</xmin>
			<ymin>25</ymin>
			<xmax>394</xmax>
			<ymax>104</ymax>
		</bndbox>
	</object>
	<object>
		<name>262232</name>
		<bndbox>
			<xmin>380</xmin>
			<ymin>25</ymin>
			<xmax>406</xmax>
			<ymax>88</ymax>
		</bndbox>
	</object>
	<object>
		<name>262237</name>
		<bndbox>
			<xmin>104</xmin>
			<ymin>81</ymin>
			<xmax>199</xmax>
			<ymax>163</ymax>
		</bndbox>
	</object>
	<object>
		<name>262238</name>
		<bndbox>
			<xmin>197</xmin>
			<ymin>60</ymin>
			<xmax>272</xmax>
			<ymax>120</ymax>
		</bndbox>
	</object>
	<object>
		<name>262238</name>
		<bndbox>
			<xmin>439</xmin>
			<ymin>49</ymin>
			<xmax>471</xmax>
			<ymax>96</ymax>
		</bndbox>
	</object>
	<object>
		<name>262238</name>
		<bndbox>
			<xmin>383</xmin>
			<ymin>30</ymin>
			<xmax>408</xmax>
			<ymax>73</ymax>
		</bndbox>
	</object>
	<object>
		<name>262239</name>
		<bndbox>
			<xmin>1</xmin>
			<ymin>48</ymin>
			<xmax>500</xmax>
			<ymax>196</ymax>
		</bndbox>
	</object>
	<object>
		<name>262234</name>
		<scene>0</scene>
		<nobndbox>1</nobndbox>
	</object>
	<object>
		<name>262235</name>
		<scene>0</scene>
		<nobndbox>1</nobndbox>
	</object>
</annotation>