<annotation>
	<filename>7343282792.jpg</filename>
	<size>
		<width>500</width>
		<height>376</height>
		<depth>3</depth>
	</size>
	<object>
		<name>268729</name>
		<bndbox>
			<xmin>68</xmin>
			<ymin>157</ymin>
			<xmax>256</xmax>
			<ymax>376</ymax>
		</bndbox>
	</object>
	<object>
		<name>268729</name>
		<bndbox>
			<xmin>223</xmin>
			<ymin>140</ymin>
			<xmax>417</xmax>
			<ymax>376</ymax>
		</bndbox>
	</object>
	<object>
		<name>268730</name>
		<bndbox>
			<xmin>59</xmin>
			<ymin>1</ymin>
			<xmax>500</xmax>
			<ymax>167</ymax>
		</bndbox>
	</object>
	<object>
		<name>268731</name>
		<bndbox>
			<xmin>229</xmin>
			<ymin>262</ymin>
			<xmax>258</xmax>
			<ymax>288</ymax>
		</bndbox>
	</object>
	<object>
		<name>268731</name>
		<bndbox>
			<xmin>217</xmin>
			<ymin>259</ymin>
			<xmax>261</xmax>
			<ymax>291</ymax>
		</bndbox>
	</object>
	<object>
		<name>268733</name>
		<bndbox>
			<xmin>2</xmin>
			<ymin>117</ymin>
			<xmax>500</xmax>
			<ymax>358</ymax>
		</bndbox>
	</object>
	<object>
		<name>268735</name>
		<bndbox>
			<xmin>226</xmin>
			<ymin>258</ymin>
			<xmax>257</xmax>
			<ymax>289</ymax>
		</bndbox>
	</object>
	<object>
		<name>268736</name>
		<bndbox>
			<xmin>313</xmin>
			<ymin>298</ymin>
			<xmax>408</xmax>
			<ymax>376</ymax>
		</bndbox>
	</object>
	<object>
		<name>268732</name>
		<scene>0</scene>
		<nobndbox>1</nobndbox>
	</object>
	<object>
		<name>268734</name>
		<scene>0</scene>
		<nobndbox>1</nobndbox>
	</object>
</annotation>